LICENSE
MANIFEST.in
README.rst
setup.py
django_wayf.egg-info/PKG-INFO
django_wayf.egg-info/SOURCES.txt
django_wayf.egg-info/dependency_links.txt
django_wayf.egg-info/not-zip-safe
django_wayf.egg-info/requires.txt
django_wayf.egg-info/top_level.txt
wayf/__init__.py
wayf/dnsutils.py
wayf/urls.py
wayf/utils.py
wayf/views.py
wayf/static/grEduPerson-1.0.schema
wayf/static/grEduPerson.schema
wayf/static/robots.txt
wayf/static/style.css
wayf/static/images/bl.gif
wayf/static/images/bottom--x.gif
wayf/static/images/bottomx--.gif
wayf/static/images/br.gif
wayf/static/images/tl.gif
wayf/static/images/top--x.gif
wayf/static/images/topx--.gif
wayf/static/images/tr.gif
wayf/templates/400.html
wayf/templates/404.html
wayf/templates/500.html
wayf/templates/base.html
wayf/templates/entity_list.html
wayf/templates/idp_dropdown.html
wayf/templates/idp_list.html
wayf/templates/sp_list.html
wayf/templates/wayf.html
wayf/templates/wayf_from_sp.html
wayf/templates/wayf_set.html