Metadata-Version: 1.1
Name: django-wayf
Version: 0.3.0
Summary: A simple Django implementation of a shibboleth/saml wayf service
Home-page: https://github.com/hpcugent/django-wayf
Author: Jens Timmerman
Author-email: jens.timmerman@ugent.be
License: GPL v3
Platform: UNKNOWN
Classifier: Environment :: Web Environment
Classifier: Framework :: Django
Classifier: Framework :: Django :: 1.8
Classifier: Intended Audience :: Developers
Classifier: License :: OSI Approved :: GNU General Public License v3 (GPLv3)
Classifier: Operating System :: OS Independent
Classifier: Programming Language :: Python
Classifier: Programming Language :: Python :: 2
Classifier: Programming Language :: Python :: 2.6
Classifier: Programming Language :: Python :: 2.7
Classifier: Topic :: Internet :: WWW/HTTP
Classifier: Topic :: Internet :: WWW/HTTP :: Dynamic Content
